[
 {
  "directory": "/home/mhaan/core/cpp_modules/cpp06/ex01",
  "arguments": [
   "g++",
   "-Wall",
   "-Wextra",
   "-Werror",
   "-std=c++17",
   "-I",
   "include",
   "-c",
   "src/main.cpp",
   "-o",
   "obj/main.o"
  ],
  "file": "src/main.cpp"
 },
 {
  "directory": "/home/mhaan/core/cpp_modules/cpp06/ex01",
  "arguments": [
   "g++",
   "-Wall",
   "-Wextra",
   "-Werror",
   "-std=c++17",
   "-I",
   "include",
   "-c",
   "src/Serializer.cpp",
   "-o",
   "obj/Serializer.o"
  ],
  "file": "src/Serializer.cpp"
 }
]
